aioconnectors/__init__.py
aioconnectors/__main__.py
aioconnectors/api.py
aioconnectors/applications.py
aioconnectors/connection.py
aioconnectors/core.py
aioconnectors/helpers.py
aioconnectors/ssl_helper.py
aioconnectors-1.6.3.dist-info/LICENSE
aioconnectors-1.6.3.dist-info/METADATA
aioconnectors-1.6.3.dist-info/WHEEL
aioconnectors-1.6.3.dist-info/top_level.txt
aioconnectors-1.6.3.dist-info/RECORD
