Metadata-Version: 2.1
Name: aioconnectors
Version: 1.6.3
Summary: Simple secure asynchronous message queue
Home-page: https://github.com/mori-b/aioconnectors
Author: Mori Benech
Author-email: moribirom@gmail.com
License: UNKNOWN
Keywords: message queue,broker,asyncio,simple,easy
Platform: UNKNOWN
Classifier: Development Status :: 5 - Production/Stable
Classifier: Intended Audience :: Developers
Classifier: Topic :: Software Development :: Libraries
Classifier: License :: OSI Approved :: Apache Software License
Classifier: Programming Language :: Python :: 3
Requires-Python: >=3.6
License-File: LICENSE
